Metadata-Version: 1.0
Name: fucking-music
Version: 0.0.1a0
Summary: Implementation of a musical system of notes, keys and chords
Home-page: UNKNOWN
Author: UNKNOWN
Author-email: lollipopnote8@gmail.com
License: UNKNOWN
Platform: UNKNOWN
